protodeep/__init__.py
protodeep/blackboxprotobuf/__init__.py
protodeep/blackboxprotobuf/lib/__init__.py
protodeep/blackboxprotobuf/lib/api.py
protodeep/blackboxprotobuf/lib/config.py
protodeep/blackboxprotobuf/lib/exceptions.py
protodeep/blackboxprotobuf/lib/protofile.py
protodeep/blackboxprotobuf/lib/types/__init__.py
protodeep/blackboxprotobuf/lib/types/fixed.py
protodeep/blackboxprotobuf/lib/types/length_delim.py
protodeep/blackboxprotobuf/lib/types/type_maps.py
protodeep/blackboxprotobuf/lib/types/varint.py
protodeep/cli.py
protodeep/internals.py
protodeep/lib.py
protodeep/modules/__init__.py
protodeep/modules/analyze.py
protodeep/protodeep.py
protodeep/utils.py
protodeep-1.1.2.dist-info/entry_points.txt
protodeep-1.1.2.dist-info/LICENSE
protodeep-1.1.2.dist-info/METADATA
protodeep-1.1.2.dist-info/WHEEL
protodeep-1.1.2.dist-info/RECORD
