Metadata-Version: 2.1
Name: protodeep
Version: 1.1.2
Summary: A tool to help reversing protobuf.
License: MIT
Author: mxrch
Author-email: mxrch.dev@pm.me
Requires-Python: >=3.10,<4.0
Classifier: License :: OSI Approved :: MIT License
Classifier: Programming Language :: Python :: 3
Classifier: Programming Language :: Python :: 3.10
Classifier: Programming Language :: Python :: 3.11
Classifier: Programming Language :: Python :: 3.12
Requires-Dist: grpcio-tools (>=1.66.2,<2.0.0)
Requires-Dist: protobuf (>=5.28.2,<6.0.0)
Requires-Dist: rich (>=13.9.1,<14.0.0)
Requires-Dist: rich-argparse (>=1.5.2,<2.0.0)
Requires-Dist: six (>=1.16.0,<2.0.0)
